CNN/PE_new.v
module PE_new#(
    parameter d_width = 32,
    parameter a_width = 8
)
(
    input clk, rst_n,
    input [3:0] kernel_size,
    input [3:0] iact_size,
    input [d_width - 1 : 0] weight, 
    input [d_width - 1 : 0] iact,

    output reg load_iact, load_weight,
    output [d_width - 1 : 0] psum0, psum1, psum2,
    output [d_width - 1 : 0] weight0, weight1, weight2, iact0, iact1, iact2, iact3, iact4
);

    reg [d_width - 1 : 0] buffer_weight [0 : 4];
    reg [d_width - 1 : 0] buffer_iact [0 : 5];
    reg [d_width - 1 : 0] buffer_out [0 : 2];

    reg [3:0] cnt_weight, cnt_iact;
    reg [3:0] cnt_kernel_size, cnt_iact_size;
    reg [3:0] index_out;

    // Load iact values
    always @(posedge clk, negedge rst_n) begin
    if (~rst_n) begin
        cnt_iact <= 0;
        load_iact <= 0;
    end 
    else begin
        if (cnt_iact < iact_size) begin
            buffer_iact[cnt_iact] <= iact;  // Ghi dữ liệu đúng ngay clk đầu tiên
            cnt_iact <= cnt_iact + 1;
        end
		  else begin
				load_iact <= 1;
		  end
    end 
end

    // Load weight values
    always @(posedge clk, negedge rst_n) begin
        if (rst_n == 0) begin
            cnt_weight <= 0;
            load_weight <= 0;
        end 
        else if (cnt_weight < kernel_size) begin
            buffer_weight[cnt_weight] <= weight;
            cnt_weight <= cnt_weight + 1;
        end 
        else begin
            load_weight <= 1;
        end
    end

    always @(posedge clk or negedge rst_n) begin
        if (rst_n == 0) begin
            buffer_out[0] <= 0;
            buffer_out[1] <= 0;
            buffer_out[2] <= 0;
            cnt_kernel_size <= 0;
            cnt_iact_size <= 0;
            index_out <= 0;
        end 
        else if (load_iact && load_weight) begin
            if (cnt_kernel_size < kernel_size) begin
                buffer_out[index_out] <= buffer_out[index_out] + buffer_iact[cnt_iact_size] * buffer_weight[cnt_kernel_size];
                cnt_kernel_size <= cnt_kernel_size + 1;
                cnt_iact_size <= cnt_iact_size + 1;
            end 
            else begin
                if (index_out < (iact_size - kernel_size + 1)) begin
                    index_out <= index_out + 1;
                    cnt_kernel_size <= 0;
                    cnt_iact_size <= index_out + 1;
                end
            end
        end
    end
	 

    assign weight0 = buffer_weight[0];
    assign weight1 = buffer_weight[1];
    assign weight2 = buffer_weight[2];

    assign iact0 = buffer_iact[0];
    assign iact1 = buffer_iact[1];
    assign iact2 = buffer_iact[2];
    assign iact3 = buffer_iact[3];
    assign iact4 = buffer_iact[4];

    assign psum0 = buffer_out[0];
    assign psum1 = buffer_out[1];
    assign psum2 = buffer_out[2];

endmodule

CNN/PE_new_tb.v
`timescale 1ns/1ps
`include "PE_new.v"
`timescale 1ns/1ps

module PE_new_tb;

    // Thông số của PE
    parameter d_width = 32;
    parameter a_width = 8;

    // Tín hiệu testbench
    reg clk, rst_n;
    reg [3:0] kernel_size;
    reg [3:0] iact_size;
    reg [d_width - 1 : 0] weight;
    reg [d_width - 1 : 0] iact;
    
    wire load_iact, load_weight;
    wire [d_width - 1 : 0] psum0, psum1, psum2;
    wire [d_width - 1 : 0] weight0, weight1, weight2, iact0, iact1, iact2, iact3, iact4;

    // Gọi module PE
    PE_new#(
        .d_width(d_width),
        .a_width(a_width)
    ) dut (
        .clk(clk),
        .rst_n(rst_n),
        .kernel_size(kernel_size),
        .iact_size(iact_size),
        .weight(weight),
        .iact(iact),
        .load_iact(load_iact),
        .load_weight(load_weight),
        .psum0(psum0),
        .psum1(psum1),
        .psum2(psum2),
        .weight0(weight0),
        .weight1(weight1),
        .weight2(weight2),
        .iact0(iact0),
        .iact1(iact1),
        .iact2(iact2),
        .iact3(iact3),
        .iact4(iact4)
    );

    // Clock 10ns (100MHz)
    always #5 clk = ~clk;

    initial begin
    // Khởi tạo tín hiệu
    $dumpfile("PE_new_tb.vcd");
    $dumpvars(0, PE_new_tb);
    clk = 0;
    rst_n = 1;
    kernel_size = 3;
    iact_size = 5;
    weight = 0;
    iact = 0;

    // Reset hệ thống
    #5 rst_n = 0;
    #5 rst_n = 1;

    // Cấp dữ liệu weight
    #5 weight = 32'd2; iact = 32'd1;
    #10 weight = 32'd3; iact = 32'd2;
    #10 weight = 32'd4; iact = 32'd3; 
    // Cấp dữ liệu iact
    #10 iact = 32'd4; 
    #10 iact = 32'd5; 

    // Chờ tính toán hoàn tất
    #200;
    // Kiểm tra đầu ra
    $display("Iact buffer:");
    $display("%d %d %d %d %d", iact0, iact1, iact2, iact3, iact4);

    $display("Weight buffer:");
    $display("%d %d %d", weight0, weight1, weight2);

    $display(psum0, psum1, psum2);

    // Kết thúc mô phỏng
    $finish;
end

endmodule

CNN/PE_new_tb.vcd
$date
	Sun Mar 09 20:25:11 2025
$end
$version
	Icarus Verilog
$end
$timescale
	1ps
$end
$scope module PE_new_tb $end
$var wire 32 ! weight2 [31:0] $end
$var wire 32 " weight1 [31:0] $end
$var wire 32 # weight0 [31:0] $end
$var wire 32 $ psum2 [31:0] $end
$var wire 32 % psum1 [31:0] $end
$var wire 32 & psum0 [31:0] $end
$var wire 1 ' load_weight $end
$var wire 1 ( load_iact $end
$var wire 32 ) iact4 [31:0] $end
$var wire 32 * iact3 [31:0] $end
$var wire 32 + iact2 [31:0] $end
$var wire 32 , iact1 [31:0] $end
$var wire 32 - iact0 [31:0] $end
$var reg 1 . clk $end
$var reg 32 / iact [31:0] $end
$var reg 4 0 iact_size [3:0] $end
$var reg 4 1 kernel_size [3:0] $end
$var reg 1 2 rst_n $end
$var reg 32 3 weight [31:0] $end
$scope module dut $end
$var wire 1 . clk $end
$var wire 32 4 iact [31:0] $end
$var wire 32 5 iact0 [31:0] $end
$var wire 32 6 iact1 [31:0] $end
$var wire 32 7 iact2 [31:0] $end
$var wire 32 8 iact3 [31:0] $end
$var wire 32 9 iact4 [31:0] $end
$var wire 4 : iact_size [3:0] $end
$var wire 4 ; kernel_size [3:0] $end
$var wire 32 < psum0 [31:0] $end
$var wire 32 = psum1 [31:0] $end
$var wire 32 > psum2 [31:0] $end
$var wire 1 2 rst_n $end
$var wire 32 ? weight [31:0] $end
$var wire 32 @ weight0 [31:0] $end
$var wire 32 A weight1 [31:0] $end
$var wire 32 B weight2 [31:0] $end
$var reg 4 C cnt_iact [3:0] $end
$var reg 4 D cnt_iact_size [3:0] $end
$var reg 4 E cnt_kernel_size [3:0] $end
$var reg 4 F cnt_weight [3:0] $end
$var reg 4 G index_out [3:0] $end
$var reg 1 ( load_iact $end
$var reg 1 ' load_weight $end
$upscope $end
$upscope $end
$enddefinitions $end
#0
$dumpvars
bx G
bx F
bx E
bx D
bx C
bx B
bx A
bx @
b0 ?
bx >
bx =
bx <
b11 ;
b101 :
bx 9
bx 8
bx 7
bx 6
bx 5
b0 4
b0 3
12
b11 1
b101 0
b0 /
0.
bx -
bx ,
bx +
bx *
bx )
x(
x'
bx &
bx %
bx $
bx #
bx "
bx !
$end
#5000
0(
b0 C
0'
b0 F
b0 G
b0 D
b0 E
b0 $
b0 >
b0 %
b0 =
b0 &
b0 <
02
1.
#10000
12
0.
#15000
b1 F
b10 #
b10 @
b1 C
b1 -
b1 5
b1 /
b1 4
b10 3
b10 ?
1.
#20000
0.
#25000
b10 C
b10 ,
b10 6
b10 F
b11 "
b11 A
1.
b10 /
b10 4
b11 3
b11 ?
#30000
0.
#35000
b11 F
b100 !
b100 B
b11 C
b11 +
b11 7
1.
b11 /
b11 4
b100 3
b100 ?
#40000
0.
#45000
b100 C
b100 *
b100 8
1'
1.
b100 /
b100 4
#50000
0.
#55000
b101 C
b101 )
b101 9
1.
b101 /
b101 4
#60000
0.
#65000
1(
1.
#70000
0.
#75000
b1 D
b1 E
b10 &
b10 <
1.
#80000
0.
#85000
b10 D
b10 E
b1000 &
b1000 <
1.
#90000
0.
#95000
b11 D
b11 E
b10100 &
b10100 <
1.
#100000
0.
#105000
b1 D
b0 E
b1 G
1.
#110000
0.
#115000
b10 D
b1 E
b100 %
b100 =
1.
#120000
0.
#125000
b11 D
b10 E
b1101 %
b1101 =
1.
#130000
0.
#135000
b100 D
b11 E
b11101 %
b11101 =
1.
#140000
0.
#145000
b10 D
b0 E
b10 G
1.
#150000
0.
#155000
b11 D
b1 E
b110 $
b110 >
1.
#160000
0.
#165000
b100 D
b10 E
b10010 $
b10010 >
1.
#170000
0.
#175000
b101 D
b11 E
b100110 $
b100110 >
1.
#180000
0.
#185000
b11 D
b0 E
b11 G
1.
#190000
0.
#195000
b100 D
b1 E
1.
#200000
0.
#205000
b101 D
b10 E
1.
#210000
0.
#215000
b110 D
b11 E
1.
