CNN/SPad.v
module SPad#(
    parameter d_width = 32,
    parameter a_width = 8
)
(
    input clk, rst_n, 
    input wen, ren,
    input [a_width -1 : 0] w_addr,
    input [d_width -1 : 0] w_data,
    input [a_width -1 : 0] r_addr,
    output reg [d_width - 1: 0] r_data 
);

    integer i;
    reg [d_width -1 : 0] mem [0:256];


    always @(posedge clk, negedge rst_n) begin
        if(~rst_n) begin
            for(i = 0; i < 256; i = i + 1) begin
                mem[i] <= 32'd0;
            end
        end
        else 
            if(wen) begin
                mem[w_addr] <= w_data;
            end
    end

    always @(posedge clk) begin
        if (ren) begin
            r_data <= mem[r_addr]; // Đọc dữ liệu từ bộ nhớ
        end
    end

endmodule

CNN/PE.v
`include "SPad.v"

module PE#(
    parameter d_width = 32,
    parameter a_width = 8,
    parameter iact_size =  5,
    parameter kernel_size = 3
)
(
    input start,
    input clk, rst_n,
    input [d_width -1 : 0] weight,
    input [d_width -1 : 0] iact,

    output reg load_weight,
    output reg load_iact,
    output reg done,
    output reg [d_width -1 : 0] pe_out
);

    reg [2:0] state, next_state;
    parameter S0 = 3'd0;
    parameter S1 = 3'd1;
    parameter S2 = 3'd2;
    parameter S3 = 3'd3;
    parameter S4 = 3'd4;

    reg [d_width -1 : 0] buffer_iact [0:4];
    reg [d_width -1 : 0] buffer_weight[0:4];
    reg [d_width -1 : 0] buffer_out[0:2];

    reg [2:0] cnt_load_iact, cnt_load_weight;
    reg [2:0] cnt_com_iact, cnt_com_weight, index_out;

    integer i;
    always@(posedge clk, negedge rst_n) begin
        if(!rst_n) begin
            state <= S0;
            cnt_com_iact <= 0;
            cnt_com_weight <= 0;
            cnt_load_iact <= 0;
            cnt_load_weight <= 0;
            index_out <= 0;
            load_iact <= 0;
            load_weight <= 0;
            done <= 0;
            pe_out <= 0;
            // Reset buffer_out
            for (i = 0; i < 3; i = i + 1) begin
              buffer_out[i] <= 0;
            end
            
        end
        else begin
            case(state) 
                S0: begin 
                    done <= 0;
                    if(start) state <= S1;
                    else begin
                        state <= S0;
                        cnt_com_iact <= 0;
                        cnt_com_weight <= 0;
                        cnt_load_iact <= 0;
                        cnt_load_weight <= 0;
                        index_out <= 0;
                        load_iact <= 0;
                        load_weight <= 0;
                        done <= 0;
                        pe_out <= 0;
                        // Reset buffer_out
                        for (i = 0; i < 3; i = i + 1) begin
                            buffer_out[i] <= 0;
                        end
                    end
                end

                S1: begin
                    if(cnt_load_iact < iact_size) begin
                        buffer_iact[cnt_load_iact] <= iact;
                        cnt_load_iact <= cnt_load_iact + 1;
                        state <= S1;
                    end
                    else begin
                        state <= S2;
                        load_iact <= 1;
                        cnt_load_iact <= 0;
                    end
                end

                S2: begin
                    if(cnt_load_weight < kernel_size) begin
                        buffer_weight[cnt_load_weight] <= weight;
                        cnt_load_weight <= cnt_load_weight + 1;
                        state <= S2;
                    end
                    else begin
                        state <= S3;
                        load_weight <= 1;
                        cnt_load_weight <= 0;
                    end
                end

                S3: begin
                    if(cnt_com_weight < kernel_size) begin
                        buffer_out[index_out] <= buffer_out[index_out] + buffer_iact[cnt_com_iact] * buffer_weight[cnt_com_weight];                        
                        cnt_com_iact <= cnt_com_iact + 1;
                        cnt_com_weight <= cnt_com_weight +1;
                        state <= S3;
                        done <= 0;
                    end
                    else begin
                        if(index_out < (iact_size - kernel_size + 1)) begin
                            index_out <= index_out + 1;
                            cnt_com_weight <= 0;
                            cnt_com_iact <= index_out + 1;
                            done <= 1;
                            pe_out <= buffer_out[index_out];
                            state <= S3;
                        end
                        else begin
                            cnt_com_iact <= 0;
                            cnt_com_weight <= 0;
                            index_out <= 0;
                            state <= S4;
                        end
                    end
                end

                S4: begin 
                    state <= S0;
                end

                default: state <= S0;
            endcase
        end
    end

endmodule

CNN/PE_tb.v
`timescale 1ns/1ps
`include "PE.v"

module PE_tb;
    parameter d_width = 32;
    parameter iact_size = 5;
    parameter kernel_size = 3;

    reg clk, rst_n, start;
    reg [d_width-1:0] weight, iact;
    wire done;
    wire load_iact, load_weight;
    wire [d_width-1:0] pe_out;

    // Instantiate the PE module
    PE #(.d_width(d_width), .iact_size(iact_size), .kernel_size(kernel_size)) 
    uut (
        .start(start),
        .clk(clk),
        .rst_n(rst_n),
        .weight(weight),
        .iact(iact),
        .done(done),
        .load_iact(load_iact),
        .load_weight(load_weight),
        .pe_out(pe_out)
    );

    // Clock generation
    always #5 clk = ~clk; // 10ns period (100MHz)

    initial begin
        // Initialize signals

        $dumpfile("PE_tb.vcd");
        $dumpvars(0, PE_tb);
        
        clk = 0;
        rst_n = 0;
        start = 0;
        weight = 0;
        iact = 0;

        // Apply reset
        #10 
        rst_n = 1;
        #10 
        start = 1;
        // Load iact values (2, 4, 6, 8, 10)
        #10;
        start = 0;
        iact = 2; 
        #10;
        iact = 4; 
        #10;
        iact = 6; 
        #10;
        iact = 8; 
        #10;
        iact = 10; 
        wait(load_iact == 1);

        #10;
        weight = 1; 
        #10;
        weight = 2; 
        #10;
        weight = 3; 
        wait(load_weight == 1);
        
        // Wait for done signal
        #200
        // Display output values
        // End simulation
        #20 $finish;
    end
endmodule

CNN/PE_tb.vcd
$date
	Mon Mar 10 14:44:04 2025
$end
$version
	Icarus Verilog
$end
$timescale
	1ps
$end
$scope module PE_tb $end
$var wire 32 ! pe_out [31:0] $end
$var wire 1 " load_weight $end
$var wire 1 # load_iact $end
$var wire 1 $ done $end
$var reg 1 % clk $end
$var reg 32 & iact [31:0] $end
$var reg 1 ' rst_n $end
$var reg 1 ( start $end
$var reg 32 ) weight [31:0] $end
$scope module uut $end
$var wire 1 % clk $end
$var wire 32 * iact [31:0] $end
$var wire 1 ' rst_n $end
$var wire 1 ( start $end
$var wire 32 + weight [31:0] $end
$var reg 3 , cnt_com_iact [2:0] $end
$var reg 3 - cnt_com_weight [2:0] $end
$var reg 3 . cnt_load_iact [2:0] $end
$var reg 3 / cnt_load_weight [2:0] $end
$var reg 1 $ done $end
$var reg 3 0 index_out [2:0] $end
$var reg 1 # load_iact $end
$var reg 1 " load_weight $end
$var reg 32 1 pe_out [31:0] $end
$var reg 3 2 state [2:0] $end
$var integer 32 3 i [31:0] $end
$upscope $end
$upscope $end
$enddefinitions $end
#0
$dumpvars
b11 3
b0 2
b0 1
b0 0
b0 /
b0 .
b0 -
b0 ,
b0 +
b0 *
b0 )
0(
0'
b0 &
0%
0$
0#
0"
b0 !
$end
#5000
b11 3
1%
#10000
0%
1'
#15000
b11 3
1%
#20000
0%
1(
#25000
b1 2
1%
#30000
0%
b10 &
b10 *
0(
#35000
b1 .
1%
#40000
0%
b100 &
b100 *
#45000
b10 .
1%
#50000
0%
b110 &
b110 *
#55000
b11 .
1%
#60000
0%
b1000 &
b1000 *
#65000
b100 .
1%
#70000
0%
b1010 &
b1010 *
#75000
b101 .
1%
#80000
0%
#85000
b0 .
1#
b10 2
1%
#90000
0%
#95000
b1 /
1%
b1 )
b1 +
#100000
0%
#105000
b10 /
1%
b10 )
b10 +
#110000
0%
#115000
b11 /
1%
b11 )
b11 +
#120000
0%
#125000
b0 /
1"
b11 2
1%
#130000
0%
#135000
b1 -
b1 ,
1%
#140000
0%
#145000
b10 -
b10 ,
1%
#150000
0%
#155000
b11 -
b11 ,
1%
#160000
0%
#165000
b11100 !
b11100 1
1$
b1 ,
b0 -
b1 0
1%
#170000
0%
#175000
0$
b1 -
b10 ,
1%
#180000
0%
#185000
b10 -
b11 ,
1%
#190000
0%
#195000
b11 -
b100 ,
1%
#200000
0%
#205000
b101000 !
b101000 1
1$
b10 ,
b0 -
b10 0
1%
#210000
0%
#215000
0$
b1 -
b11 ,
1%
#220000
0%
#225000
b10 -
b100 ,
1%
#230000
0%
#235000
b11 -
b101 ,
1%
#240000
0%
#245000
b110100 !
b110100 1
1$
b11 ,
b0 -
b11 0
1%
#250000
0%
#255000
0$
b1 -
b100 ,
1%
#260000
0%
#265000
b10 -
b101 ,
1%
#270000
0%
#275000
b11 -
b110 ,
1%
#280000
0%
#285000
b100 2
b0 0
b0 -
b0 ,
1%
#290000
0%
#295000
b0 2
1%
#300000
0%
#305000
b0 !
b0 1
0"
0#
b11 3
1%
#310000
0%
#315000
b11 3
1%
#320000
0%
#325000
b11 3
1%
#330000
0%
#335000
b11 3
1%
#340000
0%
#345000
b11 3
1%
