CNN/SPad.v
module SPad#(
    parameter d_width = 32,
    parameter a_width = 8
)
(
    input clk, rst_n, 
    input wen, ren,
    input [a_width -1 : 0] w_addr,
    input [d_width -1 : 0] w_data,
    input [a_width -1 : 0] r_addr,
    output reg [d_width - 1: 0] r_data 
);

    integer i;
    reg [d_width -1 : 0] mem [0:256];


    always @(posedge clk, negedge rst_n) begin
        if(~rst_n) begin
            for(i = 0; i < 256; i = i + 1) begin
                mem[i] <= 32'd0;
            end
        end
        else 
            if(wen) begin
                mem[w_addr] <= w_data;
            end
    end

    always @(posedge clk) begin
        if (ren) begin
            r_data <= mem[r_addr]; // Đọc dữ liệu từ bộ nhớ
        end
    end

endmodule

CNN/SPad_tb.v
`timescale 1ns/1ps
`include "SPad.v"

module SPad_tb;

    parameter d_width = 32;
    parameter a_width = 8;

    reg clk, rst_n, wen, ren;
    reg [a_width - 1:0] w_addr, r_addr;
    reg [d_width - 1:0] w_data;
    wire [d_width - 1:0] r_data;

    // Gọi module SPad
    SPad #(.d_width(d_width), .a_width(a_width)) uut (
        .clk(clk),
        .rst_n(rst_n),
        .wen(wen),
        .ren(ren),
        .w_addr(w_addr),
        .w_data(w_data),
        .r_addr(r_addr),
        .r_data(r_data)
    );

    // Tạo clock có chu kỳ 10ns
    always #5 clk = ~clk;

    initial begin
        $dumpfile("SPad_tb.vcd");
        $dumpvars(0, SPad_tb);

        // Khởi tạo tín hiệu
        clk = 0;
        rst_n = 1;
        wen = 0;
        ren = 0;
        w_addr = 0;
        w_data = 0;
        r_addr = 0;

        // Reset hệ thống
        #3 rst_n = 0;
        #10 rst_n = 1; // Reset xong, bộ nhớ sẽ khởi tạo 0

        // Kiểm tra bộ nhớ sau reset
        #10 ren = 1; r_addr = 8'd0; 
        #10 $display("Time: %0t | Read Addr: %d | Read Data: %d", $time, r_addr, r_data);
        
        #10 ren = 1; r_addr = 8'd1;
        #10 $display("Time: %0t | Read Addr: %d | Read Data: %d", $time, r_addr, r_data);
        ren = 0;

        // Ghi dữ liệu vào bộ nhớ
        #10 wen = 1; w_addr = 8'd0; w_data = 32'd100; 
        #10 wen = 1; w_addr = 8'd20; w_data = 32'd200;
        #10 wen = 0; // Dừng ghi

        // Đọc lại giá trị để kiểm tra
        #10 ren = 1; r_addr = 8'd0;
        #10 $display("Time: %0t | Read Addr: %d | Read Data: %d", $time, r_addr, r_data);

        #10 ren = 1; r_addr = 8'd20;
        #10 $display("Time: %0t | Read Addr: %d | Read Data: %d", $time, r_addr, r_data);

        #10 ren = 1; r_addr = 8'd5;
        #10 $display("Time: %0t | Read Addr: %d | Read Data: %d", $time, r_addr, r_data);
        ren = 0;

        // Kết thúc mô phỏng
        #50;
        $finish;
    end

endmodule

CNN/SPad_tb.vcd
$date
	Sun Mar 09 10:44:41 2025
$end
$version
	Icarus Verilog
$end
$timescale
	1ps
$end
$scope module SPad_tb $end
$var wire 32 ! r_data [31:0] $end
$var reg 1 " clk $end
$var reg 8 # r_addr [7:0] $end
$var reg 1 $ ren $end
$var reg 1 % rst_n $end
$var reg 8 & w_addr [7:0] $end
$var reg 32 ' w_data [31:0] $end
$var reg 1 ( wen $end
$scope module uut $end
$var wire 1 " clk $end
$var wire 8 ) r_addr [7:0] $end
$var wire 1 $ ren $end
$var wire 1 % rst_n $end
$var wire 8 * w_addr [7:0] $end
$var wire 32 + w_data [31:0] $end
$var wire 1 ( wen $end
$var reg 32 , r_data [31:0] $end
$var integer 32 - i [31:0] $end
$upscope $end
$upscope $end
$enddefinitions $end
#0
$dumpvars
bx -
bx ,
b0 +
b0 *
b0 )
0(
b0 '
b0 &
1%
0$
b0 #
0"
bx !
$end
#3000
b100000000 -
0%
#5000
b100000000 -
1"
#10000
0"
#13000
1%
#15000
1"
#20000
0"
#23000
1$
#25000
b0 !
b0 ,
1"
#30000
0"
#35000
1"
#40000
0"
#43000
b1 #
b1 )
#45000
1"
#50000
0"
#53000
0$
#55000
1"
#60000
0"
#63000
b1100100 '
b1100100 +
1(
#65000
1"
#70000
0"
#73000
b11001000 '
b11001000 +
b10100 &
b10100 *
#75000
1"
#80000
0"
#83000
0(
#85000
1"
#90000
0"
#93000
b0 #
b0 )
1$
#95000
b1100100 !
b1100100 ,
1"
#100000
0"
#105000
1"
#110000
0"
#113000
b10100 #
b10100 )
#115000
b11001000 !
b11001000 ,
1"
#120000
0"
#125000
1"
#130000
0"
#133000
b101 #
b101 )
#135000
b0 !
b0 ,
1"
#140000
0"
#143000
0$
